dbt_yamer/__init__.py
dbt_yamer/exceptions.py
dbt_yamer/cli/__init__.py
dbt_yamer/cli/generate_markdown.py
dbt_yamer/cli/generate_yamd.py
dbt_yamer/cli/generate_yaml.py
dbt_yamer/cli/main.py
dbt_yamer/cli/run.py
dbt_yamer/handlers/docblock.py
dbt_yamer/handlers/file_handlers.py
dbt_yamer/handlers/markdown_handlers.py
dbt_yamer/handlers/yaml_handlers.py
dbt_yamer/macros/macro_content.py
dbt_yamer/utils/dbt_utils.py
dbt_yamer/utils/security_utils.py
dbt_yamer/utils/subprocess_utils.py
dbt_yamer-0.2.7.dist-info/licenses/LICENSE
dbt_yamer-0.2.7.dist-info/METADATA
dbt_yamer-0.2.7.dist-info/WHEEL
dbt_yamer-0.2.7.dist-info/entry_points.txt
dbt_yamer-0.2.7.dist-info/top_level.txt
dbt_yamer-0.2.7.dist-info/RECORD
