Metadata-Version: 2.4
Name: dbt-yamer
Version: 0.2.7
Summary: A Python package for generating dbt schema.yml files.
Author-email: Muizz <lateefmuizz@gmail.com>
License: The MIT License
Classifier: Programming Language :: Python :: 3
Classifier: License :: OSI Approved :: MIT License
Classifier: Operating System :: OS Independent
License-File: LICENSE
Requires-Dist: click>=8.0.0
Requires-Dist: pyyaml>=5.4
Requires-Dist: jsonschema>=4.0
Requires-Dist: fuzzywuzzy>=0.18
Requires-Dist: python-Levenshtein>=0.12
Dynamic: license-file
